{"msg":"成功","data":[{"appId":"22f47a046aead1f6","model":"G05","sdkList":null,"commandList":[{"eventId":"001007002","android":"CENTRAL_LOCK","ios":"IngeekCommandCentralLock","description":"中控-上锁","commandAndroid":1,"commandIOS":1,"value":"010100","tag":1,"timeout":5,"kpre":null,"parameter":0},{"eventId":"001007001","android":"CENTRAL_UNLOCK","ios":"IngeekCommandCentralUnlock","description":"中控-解锁","commandAndroid":2,"commandIOS":2,"value":"010101","tag":1,"timeout":5,"kpre":null,"parameter":0},{"eventId":"001007004","android":"ALL_WINDOWS_CLOSE","ios":"IngeekCommandAllWindowsClose","description":"关闭全部车窗","commandAndroid":3,"commandIOS":3,"value":"020100","tag":2,"timeout":15,"kpre":null,"parameter":0},{"eventId":"001007003","android":"ALL_WINDOWS_OPEN","ios":"IngeekCommandAllWindowsOpen","description":"开启全部车窗","commandAndroid":4,"commandIOS":4,"value":"020101","tag":2,"timeout":15,"kpre":null,"parameter":0},{"eventId":"001007006","android":"SUNROOF_CLOSE","ios":"IngeekCommandSunroofClose","description":"关闭天窗","commandAndroid":5,"commandIOS":5,"value":"030100","tag":3,"timeout":50,"kpre":null,"parameter":0},{"eventId":"001007005","android":"SUNROOF_OPEN","ios":"IngeekCommandSunroofOpen","description":"开启天窗","commandAndroid":6,"commandIOS":6,"value":"030101","tag":3,"timeout":50,"kpre":null,"parameter":0},{"eventId":null,"android":"TRUNK_CLOSE","ios":"IngeekCommandTrunkClose","description":"关后备箱","commandAndroid":7,"commandIOS":7,"value":"090100","tag":9,"timeout":15,"kpre":null,"parameter":0},{"eventId":"001007007","android":"TRUNK_OPEN","ios":"IngeekCommandTrunkOpen","description":"开后备箱","commandAndroid":8,"commandIOS":8,"value":"090101","tag":9,"timeout":15,"kpre":null,"parameter":0},{"eventId":"001007009","android":"HONK_STOP","ios":"IngeekCommandHonkStop","description":"关鸣笛","commandAndroid":9,"commandIOS":9,"value":"060100","tag":6,"timeout":5,"kpre":null,"parameter":0},{"eventId":"001007008","android":"HONK_START","ios":"IngeekCommandHonkStart","description":"开鸣笛","commandAndroid":10,"commandIOS":10,"value":"060101","tag":6,"timeout":5,"kpre":null,"parameter":0},{"eventId":"001007011","android":"FLASHER_STOP","ios":"IngeekCommandFlasherStop","description":"关闪灯","commandAndroid":11,"commandIOS":11,"value":"070100","tag":7,"timeout":5,"kpre":null,"parameter":0},{"eventId":"001007010","android":"FLASHER_START","ios":"IngeekCommandFlasherStart","description":"开闪灯","commandAndroid":12,"commandIOS":12,"value":"070101","tag":7,"timeout":5,"kpre":null,"parameter":0},{"eventId":"001007012","android":"CHARGING_GUN_UNLOCK","ios":"IngeekCommandChargingPlugUnlock","description":"充电枪控制-解锁","commandAndroid":13,"commandIOS":13,"value":"230101","tag":35,"timeout":10,"kpre":null,"parameter":0},{"eventId":null,"android":"POWER_OFF","ios":"IngeekCommandPowerOff","description":"电源控制-下电","commandAndroid":17,"commandIOS":17,"value":"240100","tag":36,"timeout":10,"kpre":null,"parameter":0},{"eventId":null,"android":"POWER_ON","ios":"IngeekCommandPowerOn","description":"电源控制-上电","commandAndroid":18,"commandIOS":18,"value":"240101","tag":36,"timeout":10,"kpre":null,"parameter":0},{"eventId":null,"android":"PILOTED_PARKING_IN","ios":"IngeekCommandPilotedParkingIn","description":"遥控泊车-泊入","commandAndroid":19,"commandIOS":19,"value":"250100","tag":37,"timeout":15,"kpre":null,"parameter":0},{"eventId":null,"android":"PILOTED_PARKING_OUT","ios":"IngeekCommandPilotedParkingOut","description":"遥控泊车-泊出","commandAndroid":20,"commandIOS":20,"value":"250101","tag":37,"timeout":15,"kpre":null,"parameter":0}],"vehicleStatus":{"meta":{"version":"1.0","length":248,"headerLength":40,"littleEndian":1},"items":[{"name":"totalMileage","type":"double","length":32,"comment":"总里程","unit":"KM","operator":"","factor":null,"operator2":"","factor2":null,"warnType":null,"warnValues":null},{"name":"extensionMileage","type":"double","length":16,"comment":"续航里程","unit":"KM","operator":"","factor":null,"operator2":"","factor2":null,"warnType":null,"warnValues":null},{"name":"residualOil","type":"double","length":8,"comment":"剩余油量百分比","unit":"%","operator":"","factor":"0.5","operator2":"","factor2":null,"warnType":null,"warnValues":null},{"name":"lowOil","type":"int","length":8,"comment":"低油量显示，1显示，0不显示","unit":"","operator":"","factor":null,"operator2":"","factor2":null,"warnType":null,"warnValues":null},{"name":"voltage","type":"double","length":8,"comment":"电压","unit":"V","operator":"","factor":"0.1","operator2":"","factor2":null,"warnType":null,"warnValues":null},{"name":"carLamp","type":"int","length":1,"comment":"车灯，0关，1开","unit":"","operator":"","factor":null,"operator2":"","factor2":null,"warnType":null,"warnValues":null},{"name":"brakeFluid","type":"int","length":1,"comment":"制动液，0低，1高","unit":"","operator":"","factor":null,"operator2":"","factor2":null,"warnType":null,"warnValues":null},{"name":"driveDoorLock","type":"int","length":1,"comment":"驾驶门锁，0解锁，1上锁","unit":"","operator":"","factor":null,"operator2":"","factor2":null,"warnType":1,"warnValues":[0]},{"name":"passengerDoorLock","type":"int","length":1,"comment":"乘客门锁，0解锁，1上锁","unit":"","operator":"","factor":null,"operator2":"","factor2":null,"warnType":1,"warnValues":[0]},{"name":"drivingDoor","type":"int","length":1,"comment":"驾驶门，0关，1开","unit":"","operator":"","factor":null,"operator2":"","factor2":null,"warnType":2,"warnValues":[1]},{"name":"passengerDoor","type":"int","length":1,"comment":"乘客门，0关，1开","unit":"","operator":"","factor":null,"operator2":"","factor2":null,"warnType":2,"warnValues":[1]},{"name":"trunk","type":"int","length":1,"comment":"后备箱，0关，1开","unit":"","operator":"","factor":null,"operator2":"","factor2":null,"warnType":3,"warnValues":[1]},{"name":"leftRearDoor","type":"int","length":1,"comment":"左后门，0关，1开","unit":"","operator":"","factor":null,"operator2":"","factor2":null,"warnType":2,"warnValues":[1]},{"name":"rightRearDoor","type":"int","length":1,"comment":"右后门，0关，1开","unit":"","operator":"","factor":null,"operator2":"","factor2":null,"warnType":2,"warnValues":[1]},{"name":"skylight","type":"int8","length":4,"comment":"天窗，1完全关闭，7完全打开","unit":"","operator":"","factor":null,"operator2":"","factor2":null,"warnType":4,"warnValues":[1,2,3,5,6,7]},{"name":"powerState","type":"int","length":2,"comment":"电源状态","unit":"","operator":"","factor":null,"operator2":"","factor2":null,"warnType":6,"warnValues":[1,2,3]},{"name":"beforeHatch","type":"int","length":1,"comment":"前舱盖，0关，1开","unit":"","operator":"","factor":null,"operator2":"","factor2":null,"warnType":7,"warnValues":[1]},{"name":"flTirePressure","type":"double","length":8,"comment":"左前轮胎压","unit":"Bar","operator":"","factor":"0.1","operator2":"","factor2":null,"warnType":null,"warnValues":null},{"name":"frTirePressure","type":"double","length":8,"comment":"右前轮胎压","unit":"Bar","operator":"","factor":"0.1","operator2":"","factor2":null,"warnType":null,"warnValues":null},{"name":"rlTirePressure","type":"double","length":8,"comment":"左后轮胎压","unit":"Bar","operator":"","factor":"0.1","operator2":"","factor2":null,"warnType":null,"warnValues":null},{"name":"rrTirePressure","type":"double","length":8,"comment":"右后轮胎压","unit":"Bar","operator":"","factor":"0.1","operator2":"","factor2":null,"warnType":null,"warnValues":null},{"name":"flTireTemperature","type":"double","length":8,"comment":"左前轮胎温","unit":"°C","operator":"","factor":"50","operator2":"","factor2":null,"warnType":null,"warnValues":null},{"name":"frTireTemperature","type":"double","length":8,"comment":"右前轮胎温","unit":"°C","operator":"","factor":"50","operator2":"","factor2":null,"warnType":null,"warnValues":null},{"name":"rlTireTemperature","type":"double","length":8,"comment":"左后轮胎温","unit":"°C","operator":"","factor":"50","operator2":"","factor2":null,"warnType":null,"warnValues":null},{"name":"rrTireTemperature","type":"double","length":8,"comment":"右后轮胎温","unit":"°C","operator":"","factor":"50","operator2":"","factor2":null,"warnType":null,"warnValues":null},{"name":"particulateMatter","type":"double","length":16,"comment":"PM2.5","unit":"ug/m³","operator":"","factor":"10","operator2":"","factor2":null,"warnType":null,"warnValues":null},{"name":"protectionStatus","type":"int","length":8,"comment":"布防状态，0Armed，1PreArmed，2Disarmed，3Remind，4Alarm","unit":"","operator":"","factor":null,"operator2":"","factor2":null,"warnType":null,"warnValues":null},{"name":"averageFuelConsumption","type":"double","length":8,"comment":"平均油耗","unit":"L/100KM","operator":"","factor":"0.1","operator2":"","factor2":null,"warnType":null,"warnValues":null},{"name":"closeGuest","type":"int","length":1,"comment":"靠近迎宾，0关，1开","unit":"","operator":"","factor":null,"operator2":"","factor2":null,"warnType":null,"warnValues":null},{"name":"closeUnlock","type":"int","length":1,"comment":"靠近解锁，0关，1开","unit":"","operator":"","factor":null,"operator2":"","factor2":null,"warnType":null,"warnValues":null},{"name":"leaveClosure","type":"int","length":1,"comment":"离开闭锁，0关，1开","unit":"","operator":"","factor":null,"operator2":"","factor2":null,"warnType":null,"warnValues":null},{"name":"passiveUnlock","type":"int","length":1,"comment":"被动解锁，0关，1开","unit":"","operator":"","factor":null,"operator2":"","factor2":null,"warnType":null,"warnValues":null},{"name":"passiveAtresia","type":"int","length":1,"comment":"被动闭锁，0关，1开","unit":"","operator":"","factor":null,"operator2":"","factor2":null,"warnType":null,"warnValues":null},{"name":"FLWindow","type":"int","length":1,"comment":"FL车窗，0关，1开","unit":"","operator":"","factor":null,"operator2":"","factor2":null,"warnType":5,"warnValues":[1]},{"name":"FRWindow","type":"int","length":1,"comment":"FR车窗，0关，1开","unit":"","operator":"","factor":null,"operator2":"","factor2":null,"warnType":5,"warnValues":[1]},{"name":"RLWindow","type":"int8","length":1,"comment":"RL车窗，0关，1开","unit":"","operator":"","factor":null,"operator2":"","factor2":null,"warnType":5,"warnValues":[1]},{"name":"RRWindow","type":"int8","length":1,"comment":"RR车窗，0关，1开","unit":"","operator":"","factor":null,"operator2":"","factor2":null,"warnType":5,"warnValues":[1]},{"name":"hatchbackDoor","type":"int8","length":7,"comment":"电动掀背门","unit":"","operator":"","factor":null,"operator2":"","factor2":null,"warnType":3,"warnValues":[1,3,5]},{"name":"chargingPlugUnlocked","type":"int8","length":8,"comment":"充电枪解锁状态，0未解锁，1已解锁","unit":"","operator":"","factor":null,"operator2":"","factor2":null,"warnType":8,"warnValues":[1]}]},"nfcConfig":null}],"success":true}